automagik/__init__.py
automagik/__main__.py
automagik/auth.py
automagik/cli.py
automagik/config.py
automagik/constants.py
automagik/context.py
automagik/main.py
automagik/agents/__init__.py
automagik/agents/agno/__init__.py
automagik/agents/agno/multimodal_specialist/__init__.py
automagik/agents/agno/multimodal_specialist/agent.py
automagik/agents/agno/reasoning_team/agent.py
automagik/agents/claude_code/CLAUDE.md
automagik/agents/claude_code/__init__.py
automagik/agents/claude_code/agent.py
automagik/agents/claude_code/cli_environment.py
automagik/agents/claude_code/error_handling.py
automagik/agents/claude_code/executor_base.py
automagik/agents/claude_code/executor_factory.py
automagik/agents/claude_code/git_utils.py
automagik/agents/claude_code/log_manager.py
automagik/agents/claude_code/message_queue.py
automagik/agents/claude_code/models.py
automagik/agents/claude_code/repository_utils.py
automagik/agents/claude_code/sdk_cli_manager.py
automagik/agents/claude_code/sdk_config_manager.py
automagik/agents/claude_code/sdk_execution_strategies.py
automagik/agents/claude_code/sdk_executor.py
automagik/agents/claude_code/sdk_message_processor.py
automagik/agents/claude_code/sdk_metrics_handler.py
automagik/agents/claude_code/sdk_options_builder.py
automagik/agents/claude_code/sdk_process_manager.py
automagik/agents/claude_code/sdk_progress_tracker.py
automagik/agents/claude_code/sdk_stream_processor.py
automagik/agents/claude_code/stream_utils.py
automagik/agents/claude_code/utils.py
automagik/agents/claude_code/workflow_discovery.py
automagik/agents/claude_code/utils/__init__.py
automagik/agents/claude_code/utils/race_condition_helpers.py
automagik/agents/claude_code/utils/worktree_cleanup.py
automagik/agents/claude_code/workflows/CLAUDE.md
automagik/agents/claude_code/workflows/brain/allowed_tools.json
automagik/agents/claude_code/workflows/brain/config.json
automagik/agents/claude_code/workflows/brain/prompt.md
automagik-0.6.19.dist-info/licenses/LICENSE
automagik-0.6.19.dist-info/METADATA
automagik-0.6.19.dist-info/WHEEL
automagik-0.6.19.dist-info/entry_points.txt
automagik-0.6.19.dist-info/top_level.txt
automagik-0.6.19.dist-info/RECORD
