Metadata-Version: 2.4
Name: automagik
Version: 0.6.19
Summary: Automagik agents templates
Author-email: Felipe Rosa <felipe@namastex.ai>, Cezar Vasconcelos <cezar@namastex.ai>
License-Expression: MIT
Project-URL: Homepage, https://github.com/namastexlabs/automagik-agents
Project-URL: Repository, https://github.com/namastexlabs/automagik-agents
Project-URL: Issues, https://github.com/namastexlabs/automagik-agents/issues
Keywords: ai,agents,pydantic,fastapi,agno,generative-ai,memory
Classifier: Development Status :: 3 - Alpha
Classifier: Intended Audience :: Developers
Classifier: Programming Language :: Python :: 3
Classifier: Programming Language :: Python :: 3.12
Requires-Python: <3.13,>=3.12
License-File: LICENSE
Requires-Dist: python-dotenv>=1.0.1
Requires-Dist: notion-client>=2.3.0
Requires-Dist: rich>=13.9.4
Requires-Dist: logfire>=3.6.1
Requires-Dist: fastapi>=0.104.1
Requires-Dist: uvicorn>=0.24.0
Requires-Dist: pydantic-settings>=2.8.0
Requires-Dist: typer>=0.9.0
Requires-Dist: build>=1.2.2.post1
Requires-Dist: twine>=6.1.0
Requires-Dist: discord-py>=2.4.0
Requires-Dist: psycopg2-binary>=2.9.10
Requires-Dist: pydantic-ai-graph>=0.0.0
Requires-Dist: pydantic-ai>=0.0.36
Requires-Dist: pytest>=8.3.5
Requires-Dist: pytest-cov>=6.0.0
Requires-Dist: pytest-html>=4.1.1
Requires-Dist: pytest-json-report>=1.5.0
Requires-Dist: pytest-xdist>=3.6.1
Requires-Dist: requests>=2.32.3
Requires-Dist: ruff>=0.10.0
Requires-Dist: uv>=0.6.8
Requires-Dist: pydantic-ai-slim[duckduckgo]>=0.0.42
Requires-Dist: pip>=25.0.1
Requires-Dist: pydantic[email]>=2.10.6
Requires-Dist: pytest-asyncio>=0.26.0
Requires-Dist: google-api-python-client>=2.165.0
Requires-Dist: google-auth-httplib2>=0.2.0
Requires-Dist: google-auth-oauthlib>=1.2.1
Requires-Dist: pytz>=2025.2
Requires-Dist: httpx>=0.27.0
Requires-Dist: toml>=0.10.2
Requires-Dist: psutil>=6.0.0
Requires-Dist: docker>=7.1.0
Requires-Dist: aiofiles>=24.1.0
Requires-Dist: claude-code-sdk>=0.0.11
Requires-Dist: agno>=1.7.0
Requires-Dist: anyio>=4.9.0
Provides-Extra: dev
Requires-Dist: pytest>=8.3.5; extra == "dev"
Requires-Dist: pytest-cov>=6.0.0; extra == "dev"
Requires-Dist: pytest-html>=4.1.1; extra == "dev"
Requires-Dist: pytest-json-report>=1.5.0; extra == "dev"
Requires-Dist: pytest-xdist>=3.6.1; extra == "dev"
Requires-Dist: pytest-asyncio>=0.26.0; extra == "dev"
Requires-Dist: ruff>=0.10.0; extra == "dev"
Requires-Dist: coverage>=7.0.0; extra == "dev"
Dynamic: license-file
